Metadata-Version: 2.1
Name: mpf
Version: 0.57.3
Summary: The Mission Pinball Framework (MPF)
Author-email: The Mission Pinball Framework Team <brian@missionpinball.org>
License: MIT
Project-URL: homepage, https://missionpinball.org
Project-URL: support-forum, https://missionpinball.org/community/
Keywords: pinball
Classifier: Development Status :: 4 - Beta
Classifier: Intended Audience :: Developers
Classifier: License :: OSI Approved :: MIT License
Classifier: Programming Language :: Python :: 3.8
Classifier: Programming Language :: Python :: 3.9
Classifier: Programming Language :: Python :: 3.10
Classifier: Programming Language :: Python :: 3.11
Classifier: Natural Language :: English
Classifier: Operating System :: MacOS :: MacOS X
Classifier: Operating System :: Microsoft :: Windows
Classifier: Operating System :: POSIX :: Linux
Classifier: Topic :: Artistic Software
Classifier: Topic :: Games/Entertainment :: Arcade
Requires-Python: >=3.8
License-File: LICENSE.md
License-File: AUTHORS.md
Requires-Dist: asciimatics==1.15.0
Requires-Dist: packaging==23.2
Requires-Dist: prompt_toolkit==3.0.43
Requires-Dist: psutil==5.9.8
Requires-Dist: pyserial==3.5
Requires-Dist: pyserial-asyncio==0.6
Requires-Dist: ruamel.yaml==0.18.6
Requires-Dist: sortedcontainers==2.4.0
Requires-Dist: terminaltables==3.1.10
Requires-Dist: Pillow==9.5.0
Provides-Extra: crash-reporter
Requires-Dist: requests==2.28.2; extra == "crash-reporter"
Provides-Extra: irc
Requires-Dist: irc==19.0.1; extra == "irc"
Provides-Extra: linux-i2c
Requires-Dist: smbus2_asyncio==0.0.5; extra == "linux-i2c"
Provides-Extra: osc
Requires-Dist: python-osc==1.8.3; extra == "osc"
Provides-Extra: pin2dmd
Requires-Dist: pyusb==1.1.0; extra == "pin2dmd"
Provides-Extra: rpi
Requires-Dist: apigpio-mpf==0.0.4; extra == "rpi"
Provides-Extra: uvloop
Requires-Dist: uvloop==0.19.0; extra == "uvloop"
Provides-Extra: vpe
Requires-Dist: grpcio_tools==1.34.0; extra == "vpe"
Requires-Dist: grpcio==1.34.0; extra == "vpe"
Requires-Dist: protobuf==3.14.0; extra == "vpe"
Provides-Extra: all
Requires-Dist: prompt_toolkit==3.0.43; extra == "all"
Requires-Dist: asciimatics==1.15.0; extra == "all"
Requires-Dist: terminaltables==3.1.0; extra == "all"
Requires-Dist: requests==2.28.2; extra == "all"
Requires-Dist: irc==19.0.1; extra == "all"
Requires-Dist: smbus2_asyncio==0.0.5; extra == "all"
Requires-Dist: python-osc==1.8.3; extra == "all"
Requires-Dist: pyusb==1.1.0; extra == "all"
Requires-Dist: apigpio-mpf==0.0.4; extra == "all"
Requires-Dist: grpcio_tools==1.34.0; extra == "all"
Requires-Dist: grpcio==1.34.0; extra == "all"
Requires-Dist: protobuf==3.14.0; extra == "all"
Requires-Dist: uvloop==0.19.0; extra == "all"
